gwtransport/__init__.py
gwtransport/advection.py
gwtransport/advection_utils.py
gwtransport/deposition.py
gwtransport/diffusion.py
gwtransport/diffusion_fast.py
gwtransport/examples.py
gwtransport/gamma.py
gwtransport/logremoval.py
gwtransport/residence_time.py
gwtransport/surfacearea.py
gwtransport/utils.py
gwtransport/fronttracking/__init__.py
gwtransport/fronttracking/events.py
gwtransport/fronttracking/handlers.py
gwtransport/fronttracking/math.py
gwtransport/fronttracking/output.py
gwtransport/fronttracking/plot.py
gwtransport/fronttracking/solver.py
gwtransport/fronttracking/validation.py
gwtransport/fronttracking/waves.py
gwtransport-0.24.0.dist-info/METADATA
gwtransport-0.24.0.dist-info/WHEEL
gwtransport-0.24.0.dist-info/licenses/LICENSE
gwtransport-0.24.0.dist-info/RECORD
