Metadata-Version: 2.4
Name: gwtransport
Version: 0.24.0
Summary: Timeseries analysis for groundwater transport of solutes and heat
Project-URL: Homepage, https://github.com/gwtransport/gwtransport
Project-URL: Documentation, https://gwtransport.github.io/gwtransport
Project-URL: Sponsor, https://savethechildren.net/what-we-do/emergencies/war-gaza
Author: Bas des Tombe
License:                     GNU AFFERO GENERAL PUBLIC LICENSE
License-File: LICENSE
Keywords: analysis,aquifer,bank-filtration,contaminant,groundwater,hydrology,pathogen-removal,residence-time,temperature,time-series,transport,water-treatment
Classifier: Development Status :: 4 - Beta
Classifier: Intended Audience :: Science/Research
Classifier: License :: OSI Approved :: GNU Affero General Public License v3
Classifier: Operating System :: OS Independent
Classifier: Programming Language :: Python :: 3
Classifier: Programming Language :: Python :: 3.11
Classifier: Programming Language :: Python :: 3.12
Classifier: Programming Language :: Python :: 3.13
Classifier: Programming Language :: Python :: 3.14
Classifier: Topic :: Scientific/Engineering
Classifier: Topic :: Scientific/Engineering :: Hydrology
Classifier: Topic :: Scientific/Engineering :: Physics
Requires-Python: >=3.11
Requires-Dist: ipykernel>=4.0.1
Requires-Dist: matplotlib>=3.8.4
Requires-Dist: mpmath>=1.3.0
Requires-Dist: numpy>=2.0.0
Requires-Dist: pandas>=2.2.2
Requires-Dist: requests>=2.19.0
Requires-Dist: scipy>=1.13.0
Provides-Extra: docs
Requires-Dist: jupyter; extra == 'docs'
Requires-Dist: nbsphinx; extra == 'docs'
Requires-Dist: nbsphinx-link; extra == 'docs'
Requires-Dist: sphinx-autodoc-typehints; extra == 'docs'
Requires-Dist: sphinx-book-theme>=1.0.0; extra == 'docs'
Requires-Dist: sphinx-copybutton; extra == 'docs'
Requires-Dist: sphinx<9.0,>=7.0; extra == 'docs'
Requires-Dist: sphinxext-opengraph[social-cards]; extra == 'docs'
Provides-Extra: test
Requires-Dist: nbconvert>=7.1.0; extra == 'test'
Requires-Dist: nbformat>=5.0.2; extra == 'test'
Requires-Dist: pytest-cov>=2.3.1; extra == 'test'
Requires-Dist: pytest-xdist>=1.28.0; extra == 'test'
Requires-Dist: pytest>=6.2.5; extra == 'test'
Requires-Dist: ruff==0.13.2; extra == 'test'
Requires-Dist: ty; extra == 'test'
Requires-Dist: validate-pyproject[all,store]; extra == 'test'
